[{"match_id": "c0e3342a", "date": "2024-08-17", "time": "15:00", "round": "Matchweek 1", "league_id": null, "home_away": "Away", "opponent": "Arsenal", "opponent_id": "18bb7c10", "result": "L", "gf": 0, "ga": 2, "formation": "4-2-3-1", "attendance": "60,261", "captain": "Mario Lemina", "referee": "Jarred Gillett"}, {"match_id": "e76c15c9", "date": "2024-08-25", "time": "14:00", "round": "Matchweek 2", "league_id": null, "home_away": "Home", "opponent": "Chelsea", "opponent_id": "cff3d9bb", "result": "L", "gf": 2, "ga": 6, "formation": "4-2-3-1", "attendance": "31,235", "captain": "Mario Lemina", "referee": "Darren England"}, {"match_id": "837f0304", "date": "2024-08-31", "time": "15:00", "round": "Matchweek 3", "league_id": null, "home_away": "Away", "opponent": "Nott'ham Forest", "opponent_id": "e4a775cb", "result": "D", "gf": 1, "ga": 1, "formation": "4-4-1-1", "attendance": "29,918", "captain": "Mario Lemina", "referee": "Simon Hooper"}, {"match_id": "4b01981e", "date": "2024-09-15", "time": "16:30", "round": "Matchweek 4", "league_id": null, "home_away": "Home", "opponent": "Newcastle Utd", "opponent_id": "b2b47a98", "result": "L", "gf": 1, "ga": 2, "formation": "4-4-1-1", "attendance": "30,255", "captain": "Mario Lemina", "referee": "Chris Kavanagh"}, {"match_id": "e2b62260", "date": "2024-09-21", "time": "15:00", "round": "Matchweek 5", "league_id": null, "home_away": "Away", "opponent": "Aston Villa", "opponent_id": "8602292d", "result": "L", "gf": 1, "ga": 3, "formation": "4-1-4-1", "attendance": "39,978", "captain": "Mario Lemina", "referee": "Tim Robinson"}, {"match_id": "f2633f1d", "date": "2024-09-28", "time": "17:30", "round": "Matchweek 6", "league_id": null, "home_away": "Home", "opponent": "Liverpool", "opponent_id": "822bd0ba", "result": "L", "gf": 1, "ga": 2, "formation": "4-1-4-1", "attendance": "31,413", "captain": "Mario Lemina", "referee": "Anthony Taylor"}, {"match_id": "909090f8", "date": "2024-10-05", "time": "15:00", "round": "Matchweek 7", "league_id": null, "home_away": "Away", "opponent": "Brentford", "opponent_id": "cd051869", "result": "L", "gf": 3, "ga": 5, "formation": "4-1-4-1", "attendance": "16,960", "captain": "Mario Lemina", "referee": "Andy Madley"}, {"match_id": "90b22cd5", "date": "2024-10-20", "time": "14:00", "round": "Matchweek 8", "league_id": null, "home_away": "Home", "opponent": "Manchester City", "opponent_id": "b8fd03ef", "result": "L", "gf": 1, "ga": 2, "formation": "3-5-2", "attendance": "31,319", "captain": "Mario Lemina", "referee": "Chris Kavanagh"}, {"match_id": "9487e056", "date": "2024-10-26", "time": "15:00", "round": "Matchweek 9", "league_id": null, "home_away": "Away", "opponent": "Brighton", "opponent_id": "d07537b9", "result": "D", "gf": 2, "ga": 2, "formation": "3-4-3", "attendance": "31,840", "captain": "Mario Lemina", "referee": "Michael Oliver"}, {"match_id": "a4251fae", "date": "2024-11-02", "time": "17:30", "round": "Matchweek 10", "league_id": null, "home_away": "Home", "opponent": "Crystal Palace", "opponent_id": "47c64c55", "result": "D", "gf": 2, "ga": 2, "formation": "3-4-3", "attendance": "31,124", "captain": "N\u00e9lson Semedo", "referee": "Anthony Taylor"}, {"match_id": "dbec2d40", "date": "2024-11-09", "time": "15:00", "round": "Matchweek 11", "league_id": null, "home_away": "Home", "opponent": "Southampton", "opponent_id": "33c895d4", "result": "W", "gf": 2, "ga": 0, "formation": "4-2-3-1", "attendance": "31,403", "captain": "Mario Lemina", "referee": "Thomas Bramall"}, {"match_id": "ed24aeb8", "date": "2024-11-23", "time": "15:00", "round": "Matchweek 12", "league_id": null, "home_away": "Away", "opponent": "Fulham", "opponent_id": "fd962109", "result": "W", "gf": 4, "ga": 1, "formation": "3-4-3", "attendance": "26,685", "captain": "Mario Lemina", "referee": "Robert Jones"}, {"match_id": "adfb1b89", "date": "2024-11-30", "time": "15:00", "round": "Matchweek 13", "league_id": null, "home_away": "Home", "opponent": "Bournemouth", "opponent_id": "4ba7cbea", "result": "L", "gf": 2, "ga": 4, "formation": "4-2-3-1", "attendance": "26,685", "captain": "Mario Lemina", "referee": "Peter Bankes"}, {"match_id": "71f00b04", "date": "2024-12-04", "time": "19:30", "round": "Matchweek 14", "league_id": null, "home_away": "Away", "opponent": "Everton", "opponent_id": "d3fd31cc", "result": "L", "gf": 0, "ga": 4, "formation": "3-4-3", "attendance": "38,820", "captain": "Mario Lemina", "referee": "Michael Salisbury"}, {"match_id": "4d72ec87", "date": "2024-12-09", "time": "20:00", "round": "Matchweek 15", "league_id": null, "home_away": "Away", "opponent": "West Ham", "opponent_id": "7c21e445", "result": "L", "gf": 1, "ga": 2, "formation": "3-4-3", "attendance": "62,474", "captain": "Mario Lemina", "referee": "John Brooks"}, {"match_id": "46d52e33", "date": "2024-12-14", "time": "15:00", "round": "Matchweek 16", "league_id": null, "home_away": "Home", "opponent": "Ipswich Town", "opponent_id": "b74092de", "result": "L", "gf": 1, "ga": 2, "formation": "3-4-3", "attendance": "30,866", "captain": "N\u00e9lson Semedo", "referee": "Simon Hooper"}, {"match_id": "ecd6cb1d", "date": "2024-12-22", "time": "14:00", "round": "Matchweek 17", "league_id": null, "home_away": "Away", "opponent": "Leicester City", "opponent_id": "a2d435b3", "result": "W", "gf": 3, "ga": 0, "formation": "3-4-3", "attendance": "31,818", "captain": "N\u00e9lson Semedo", "referee": "Anthony Taylor"}, {"match_id": "77bcad49", "date": "2024-12-26", "time": "17:30", "round": "Matchweek 18", "league_id": null, "home_away": "Home", "opponent": "Manchester Utd", "opponent_id": "19538871", "result": "W", "gf": 2, "ga": 0, "formation": "3-4-3", "attendance": "31,407", "captain": "N\u00e9lson Semedo", "referee": "Tony Harrington"}, {"match_id": "3d2ef5b4", "date": "2024-12-29", "time": "15:00", "round": "Matchweek 19", "league_id": null, "home_away": "Away", "opponent": "Tottenham", "opponent_id": "361ca564", "result": "D", "gf": 2, "ga": 2, "formation": "3-4-3", "attendance": "61,284", "captain": "N\u00e9lson Semedo", "referee": "Chris Kavanagh"}, {"match_id": "56c4250a", "date": "2025-01-06", "time": "20:00", "round": "Matchweek 20", "league_id": null, "home_away": "Home", "opponent": "Nott'ham Forest", "opponent_id": "e4a775cb", "result": "L", "gf": 0, "ga": 3, "formation": "3-4-3", "attendance": "29,940", "captain": "Matt Doherty", "referee": "Peter Bankes"}, {"match_id": "535d70d7", "date": "2025-01-15", "time": "19:30", "round": "Matchweek 21", "league_id": null, "home_away": "Away", "opponent": "Newcastle Utd", "opponent_id": "b2b47a98", "result": "L", "gf": 0, "ga": 3, "formation": "3-4-3", "attendance": "51,975", "captain": "Matt Doherty", "referee": "Darren England"}, {"match_id": "e62cfa12", "date": "2025-01-20", "time": "20:00", "round": "Matchweek 22", "league_id": null, "home_away": "Away", "opponent": "Chelsea", "opponent_id": "cff3d9bb", "result": "L", "gf": 1, "ga": 3, "formation": "3-4-3", "attendance": "39,221", "captain": "N\u00e9lson Semedo", "referee": "Simon Hooper"}, {"match_id": "0b39252e", "date": "2025-01-25", "time": "15:00", "round": "Matchweek 23", "league_id": null, "home_away": "Home", "opponent": "Arsenal", "opponent_id": "18bb7c10", "result": "L", "gf": 0, "ga": 1, "formation": "3-4-3", "attendance": "31,503", "captain": "N\u00e9lson Semedo", "referee": "Michael Oliver"}, {"match_id": "693ab427", "date": "2025-02-01", "time": "17:30", "round": "Matchweek 24", "league_id": null, "home_away": "Home", "opponent": "Aston Villa", "opponent_id": "8602292d", "result": "W", "gf": 2, "ga": 0, "formation": "3-4-3", "attendance": "31,385", "captain": "N\u00e9lson Semedo", "referee": "Andy Madley"}, {"match_id": "6a917c79", "date": "2025-02-16", "time": "14:00", "round": "Matchweek 25", "league_id": null, "home_away": "Away", "opponent": "Liverpool", "opponent_id": "822bd0ba", "result": "L", "gf": 1, "ga": 2, "formation": "3-4-3", "attendance": "60,248", "captain": "N\u00e9lson Semedo", "referee": "Simon Hooper"}, {"match_id": "ccdda6d3", "date": "2025-02-22", "time": "15:00", "round": "Matchweek 26", "league_id": null, "home_away": "Away", "opponent": "Bournemouth", "opponent_id": "4ba7cbea", "result": "W", "gf": 1, "ga": 0, "formation": "3-4-3", "attendance": "11,206", "captain": "N\u00e9lson Semedo", "referee": "Michael Salisbury"}, {"match_id": "7aecfc4c", "date": "2025-02-25", "time": "19:30", "round": "Matchweek 27", "league_id": null, "home_away": "Home", "opponent": "Fulham", "opponent_id": "fd962109", "result": "L", "gf": 1, "ga": 2, "formation": "3-4-3", "attendance": "28,708", "captain": "N\u00e9lson Semedo", "referee": "Peter Bankes"}, {"match_id": "2ac7408b", "date": "2025-03-08", "time": "20:00", "round": "Matchweek 28", "league_id": null, "home_away": "Home", "opponent": "Everton", "opponent_id": "d3fd31cc", "result": "D", "gf": 1, "ga": 1, "formation": "3-4-3", "attendance": "30,738", "captain": "N\u00e9lson Semedo", "referee": "Stuart Attwell"}, {"match_id": "eea61e7f", "date": "2025-03-15", "time": "15:00", "round": "Matchweek 29", "league_id": null, "home_away": "Away", "opponent": "Southampton", "opponent_id": "33c895d4", "result": "W", "gf": 2, "ga": 1, "formation": "3-4-3", "attendance": "30,950", "captain": "N\u00e9lson Semedo", "referee": "Robert Jones"}, {"match_id": "6e6e9d8b", "date": "2025-04-01", "time": "19:45", "round": "Matchweek 30", "league_id": null, "home_away": "Home", "opponent": "West Ham", "opponent_id": "7c21e445", "result": "W", "gf": 1, "ga": 0, "formation": "3-4-3", "attendance": "29,587", "captain": "N\u00e9lson Semedo", "referee": "Tony Harrington"}, {"match_id": "b6f200da", "date": "2025-04-05", "time": "15:00", "round": "Matchweek 31", "league_id": null, "home_away": "Away", "opponent": "Ipswich Town", "opponent_id": "b74092de", "result": "W", "gf": 2, "ga": 1, "formation": "3-4-3", "attendance": "29,549", "captain": "N\u00e9lson Semedo", "referee": "Peter Bankes"}, {"match_id": "5a44bda9", "date": "2025-04-13", "time": "14:00", "round": "Matchweek 32", "league_id": null, "home_away": "Home", "opponent": "Tottenham", "opponent_id": "361ca564", "result": "W", "gf": 4, "ga": 2, "formation": "3-4-3", "attendance": "31,463", "captain": "N\u00e9lson Semedo", "referee": "Anthony Taylor"}, {"match_id": "e50fd749", "date": "2025-04-20", "time": "14:00", "round": "Matchweek 33", "league_id": null, "home_away": "Away", "opponent": "Manchester Utd", "opponent_id": "19538871", "result": "W", "gf": 1, "ga": 0, "formation": "3-4-3", "attendance": "73,819", "captain": "N\u00e9lson Semedo", "referee": "Robert Jones"}, {"match_id": "1ced4069", "date": "2025-04-26", "time": "15:00", "round": "Matchweek 34", "league_id": null, "home_away": "Home", "opponent": "Leicester City", "opponent_id": "a2d435b3", "result": "W", "gf": 3, "ga": 0, "formation": "3-4-3", "attendance": "31,518", "captain": "N\u00e9lson Semedo", "referee": "Samuel Barrott"}, {"match_id": "6a433468", "date": "2025-05-02", "time": "20:00", "round": "Matchweek 35", "league_id": null, "home_away": "Away", "opponent": "Manchester City", "opponent_id": "b8fd03ef", "result": "L", "gf": 0, "ga": 1, "formation": "3-4-3", "attendance": "53,282", "captain": "N\u00e9lson Semedo", "referee": "Peter Bankes"}, {"match_id": "f1bf04cb", "date": "2025-05-10", "time": "15:00", "round": "Matchweek 36", "league_id": null, "home_away": "Home", "opponent": "Brighton", "opponent_id": "d07537b9", "result": "L", "gf": 0, "ga": 2, "formation": "3-4-3", "attendance": "31,279", "captain": "N\u00e9lson Semedo", "referee": "Michael Oliver"}, {"match_id": "f85454d3", "date": "2025-05-20", "time": "20:00", "round": "Matchweek 37", "league_id": null, "home_away": "Away", "opponent": "Crystal Palace", "opponent_id": "47c64c55", "result": "L", "gf": 2, "ga": 4, "formation": "3-4-3", "attendance": "24,766", "captain": "Toti Gomes", "referee": "David Webb"}, {"match_id": "812ef8ad", "date": "2025-05-25", "time": "16:00", "round": "Matchweek 38", "league_id": null, "home_away": "Home", "opponent": "Brentford", "opponent_id": "cd051869", "result": "D", "gf": 1, "ga": 1, "formation": "3-4-3", "attendance": "31,382", "captain": "N\u00e9lson Semedo", "referee": "Craig Pawson"}]